{
    "_links": {
        "self": {
            "href": "http:\/\/default\/zusammenleben\/nachtruhe?_format=hal_json"
        },
        "type": {
            "href": "http:\/\/drupal.org\/rest\/type\/taxonomy_term\/topic_tree"
        },
        "http:\/\/drupal.org\/rest\/relation\/taxonomy_term\/topic_tree\/parent": [
            {
                "href": "http:\/\/default\/zusammenleben?_format=hal_json"
            }
        ]
    },
    "tid": [
        {
            "value": 10
        }
    ],
    "uuid": [
        {
            "value": "36799b00-1059-4d50-bbf1-2f7ce912461e"
        }
    ],
    "langcode": [
        {
            "value": "en",
            "lang": "en"
        }
    ],
    "vid": [
        {
            "target_id": "topic_tree"
        }
    ],
    "name": [
        {
            "value": "Nachtruhe",
            "lang": "en"
        }
    ],
    "weight": [
        {
            "value": 2
        }
    ],
    "_embedded": {
        "http:\/\/drupal.org\/rest\/relation\/taxonomy_term\/topic_tree\/parent": [
            {
                "_links": {
                    "self": {
                        "href": "http:\/\/default\/zusammenleben?_format=hal_json"
                    },
                    "type": {
                        "href": "http:\/\/drupal.org\/rest\/type\/taxonomy_term\/topic_tree"
                    }
                },
                "uuid": [
                    {
                        "value": "b0e49b5f-43a9-4414-bd30-37cf4f84b136"
                    }
                ]
            }
        ]
    },
    "changed": [
        {
            "value": "2017-10-20T12:00:41+00:00",
            "lang": "en",
            "format": "Y-m-d\\TH:i:sP"
        }
    ],
    "default_langcode": [
        {
            "value": true,
            "lang": "en"
        }
    ],
    "path": [
        {
            "alias": "\/zusammenleben\/nachtruhe",
            "pid": 10,
            "langcode": "en",
            "lang": "en"
        }
    ]
}